app/__init__.py
app/main.py
app/utils.py
cadziu-0.6.dist-info/METADATA
cadziu-0.6.dist-info/WHEEL
cadziu-0.6.dist-info/entry_points.txt
cadziu-0.6.dist-info/top_level.txt
cadziu-0.6.dist-info/RECORD
