Metadata-Version: 2.1
Name: cadziu
Version: 0.6
Summary: A tool to manage Caddy reverse proxy configurations with Cloudflare DNS.
Home-page: https://github.com/yourusername/cadziu
Author: Your Name
Author-email: your.email@example.com
Classifier: Programming Language :: Python :: 3
Classifier: License :: OSI Approved :: MIT License
Classifier: Operating System :: OS Independent
Requires-Python: >=3.6
Requires-Dist: requests
Requires-Dist: python-dotenv
